chunkfile/ChunkFile.py
chunkfile/__init__.py
chunkfile-1.0.0b2.dist-info/top_level.txt
chunkfile-1.0.0b2.dist-info/METADATA
chunkfile-1.0.0b2.dist-info/DESCRIPTION.rst
chunkfile-1.0.0b2.dist-info/metadata.json
chunkfile-1.0.0b2.dist-info/WHEEL
chunkfile-1.0.0b2.dist-info/RECORD
