Metadata-Version: 2.0
Name: chunkfile
Version: 1.0.0b2
Summary: A file-like interface backed by multiple smaller files.
Home-page: https://github.com/oneup40/chunkfile
Author: oneup40
Author-email: oneup40@gmail.com
License: Free for non-commercial use
Download-URL: https://github.com/oneup40/chunkfile/archive/v1.0.0-b2.tar.gz
Keywords: chunk file filesystem
Platform: UNKNOWN
Classifier: Development Status :: 4 - Beta
Classifier: Intended Audience :: Developers
Classifier: License :: Free for non-commercial use
Classifier: Operating System :: POSIX :: Linux
Classifier: Programming Language :: Python :: 2.6
Classifier: Programming Language :: Python :: 2.7
Classifier: Programming Language :: Python :: 3.3
Classifier: Programming Language :: Python :: 3.4
Classifier: Programming Language :: Python :: 3.5
Classifier: Programming Language :: Python :: 3.6
Classifier: Topic :: Software Development :: Libraries
Classifier: Topic :: System :: Filesystems
Requires-Dist: pathlib
